README.md
setup.py
rvfln/__init__.py
rvfln/rvfln_code.py
rvfln.egg-info/PKG-INFO
rvfln.egg-info/SOURCES.txt
rvfln.egg-info/dependency_links.txt
rvfln.egg-info/top_level.txt