Metadata-Version: 2.1
Name: rvfln
Version: 0.0.4
Summary: Package for an implementation of Random Vector Functional Link Network. For the user's convenience the package uses Sklearn's API
Home-page: UNKNOWN
Author: Márton Kardos
License: UNKNOWN
Platform: UNKNOWN
